gf180_hdl21
