Metadata-Version: 2.1
Name: gf180-hdl21
Version: 4.0.0
Summary: Global Foundries 180nm MCU PDK Package for Hdl21
Home-page: https://github.com/dan-fritchman/Hdl21
Author: Dan Fritchman, Thomas Pluck
Requires-Python: >=3.7
Provides-Extra: dev
